Workbook

Sheet Cover
B4: Project Bloom
B6: 株式会社ルミエールボーテ LBOファイナンシャルモデル
B8: ケース：Bank Base Case（ベースケース（銀行調整））
B10: 会社名 | D10: 株式会社ルミエールボーテ
B11: 事業内容 | D11: 化粧品・スキンケアの企画販売（D2C・卸）
B12: 借入人（SPC） | D12: 株式会社ブルームホールディングス（本件買収のための特別目的会社）
B13: スポンサー | D13: 大手町プリンシパルパートナーズ株式会社
B14: 直近決算期 | D14: 2026年3月期（2026/3期）
B15: クローズ予定日 | D15: 2026年11月30日
B16: 通貨・単位 | D16: JPY・百万円（million）
B17: 作成 | D17: 大手町プリンシパルパートナーズ株式会社 投資チーム
B18: 作成日 | D18: 2026年6月20日（Ver. 2.3）
B21: 【取扱厳重注意】
B22: 本資料は貴行における本件検討のためにのみ作成されたものであり、作成者の事前の書面による同意なく第三者への開示・複製を禁じます。
B23: 本資料に含まれる将来予測は多くの前提・仮定に基づくものであり、その実現性を保証するものではありません。

Sheet inp
A1: 前提条件・KPIドライバー（inp）
A2: （単位：百万円。人数・円・％は行ラベルに明記） | H2: ケース: Bank Base Case
B6: ストラクチャー（Sources & Uses・のれん）
B8: エンタープライズ・バリュー（EV） | D8: 9000
B9: EV/EBITDA倍率（2026/3期実績対比） | D9: 8
B10: 株式対価（想定） | D10: 9220
B11: シニアタームローンA | D11: 4800
B12: スポンサーエクイティ | D12: 4620
B13: 既存借入リファイナンス | D13: 400
B14: アドバイザリー・取引費用等 | D14: 180
B15: 対象会社手元現金の活用 | D15: 380
B16: のれん想定額（暫定PPA前） | D16: 6100
B17: ローン期間（年） | D17: 7
B18: 適用金利（TIBOR+230bp想定） | D18: 0.023
B19: 約定弁済（年・最終回残額一括） | D19: 480
B21: スポンサー提示EBITDA（2026/3期実績・速報） | D21: 1120
B22: クローズ予定日 | D22: 2026年11月30日
B23: 借入人（SPC） | D23: 株式会社ブルームホールディングス
B25: ※ のれん想定額 = 株式対価9,220 − 時価純資産2,655 − 識別無形資産465（暫定PPA前・財務DDの時価純資産評価に基づく）
B26: KPIドライバー（Operating Assumptions）
C27: 2024/3期 | D27: 2025/3期 | E27: 2026/3期 | F27: 2027/3期 | G27: 2028/3期 | H27: 2029/3期 | I27: 2030/3期 | J27: 2031/3期
C28: A（実績） | D28: A（実績） | E28: A（実績） | F28: P（計画） | G28: P（計画） | H28: P（計画） | I28: P（計画） | J28: P（計画）
B30: アクティブ会員数（人） | C30: 196000 | D30: 212000 | E30: 228000 | F30: =ROUND(E30*F31+F32,0) -> 239280 | G30: =ROUND(F30*G31+G32,0) -> 247853 | H30: =ROUND(G30*H31+H32,0) -> 254368 | I30: =ROUND(H30*I31+I32,0) -> 259320 | J30: =ROUND(I30*J31+J32,0) -> 263083
B31: リピート率（既存会員残存率） | C31: 0.74 | D31: 0.75 | E31: 0.76 | F31: 0.76 | G31: 0.76 | H31: 0.76 | I31: 0.76 | J31: 0.76
B32: 新規獲得会員数（人） | C32: 58000 | D32: 65000 | E32: 69000 | F32: 66000 | G32: 66000 | H32: 66000 | I32: 66000 | J32: 66000
B33: 年間平均購入回数（回） | C33: 2.45 | D33: 2.52 | E33: 2.6 | F33: 2.6 | G33: 2.61 | H33: 2.62 | I33: 2.64 | J33: 2.65
B34: 平均注文単価（AOV・円） | C34: 6400 | D34: 6520 | E34: 6650 | F34: 6720 | G34: 6790 | H34: 6860 | I34: 6930 | J34: 7000
B35: 卸取扱店舗数（店） | C35: 3980 | D35: 4060 | E35: 4150 | F35: 4200 | G35: 4240 | H35: 4280 | I35: 4320 | J35: 4350
B36: 店舗あたり年間出荷額（千円） | C36: 930 | D36: 975 | E36: 1010 | F36: 1020 | G36: 1028 | H36: 1035 | I36: 1043 | J36: 1050
B37: 売上原価率（対売上） | C37: 0.42 | D37: 0.415 | E37: 0.41 | F37: 0.41 | G37: 0.41 | H37: 0.41 | I37: 0.41 | J37: 0.41
B38: 広告宣伝費率（対売上） | C38: 0.17 | D38: 0.175 | E38: 0.18 | F38: 0.18 | G38: 0.18 | H38: 0.18 | I38: 0.18 | J38: 0.18
B39: 物流費率（対売上） | C39: 0.082 | D39: 0.081 | E39: 0.08 | F39: 0.08 | G39: 0.08 | H39: 0.08 | I39: 0.08 | J39: 0.08
B41: 設備投資（年間） | F41: 170 | G41: 170 | H41: 170 | I41: 170 | J41: 170
B43: ※ アクティブ会員数（計画年）= 前期会員数 × リピート率 ＋ 新規獲得会員数

Sheet PL
A1: 損益計算書（Projected P&L）
A2: （単位：百万円） | H2: ケース: Bank Base Case
C4: 2024/3期 | D4: 2025/3期 | E4: 2026/3期 | F4: 2027/3期 | G4: 2028/3期 | H4: 2029/3期 | I4: 2030/3期 | J4: 2031/3期
C5: A（実績） | D5: A（実績） | E5: A（実績） | F5: P（計画） | G5: P（計画） | H5: P（計画） | I5: P（計画） | J5: P（計画）
B7: EC売上（自社EC・モール計） | C7: 3073 | D7: 3483 | E7: 3942 | F7: =ROUND(inp!F30*inp!F33*inp!F34/10^6,0) -> 4181 | G7: =ROUND(inp!G30*inp!G33*inp!G34/10^6,0) -> 4392 | H7: =ROUND(inp!H30*inp!H33*inp!H34/10^6,0) -> 4572 | I7: =ROUND(inp!I30*inp!I33*inp!I34/10^6,0) -> 4744 | J7: =ROUND(inp!J30*inp!J33*inp!J34/10^6,0) -> 4880
B8: 卸売上（ドラッグストア・バラエティ） | C8: 3701 | D8: 3959 | E8: 4192 | F8: =ROUND(inp!F35*inp!F36/1000,0) -> 4284 | G8: =ROUND(inp!G35*inp!G36/1000,0) -> 4359 | H8: =ROUND(inp!H35*inp!H36/1000,0) -> 4430 | I8: =ROUND(inp!I35*inp!I36/1000,0) -> 4506 | J8: =ROUND(inp!J35*inp!J36/1000,0) -> 4568
B9: その他売上（百貨店・海外） | C9: 1014 | D9: 1058 | E9: 1106 | F9: 1130 | G9: 1155 | H9: 1180 | I9: 1205 | J9: 1230
B10: 売上収益 合計 | C10: =SUM(C7:C9) -> 7788 | D10: =SUM(D7:D9) -> 8500 | E10: =SUM(E7:E9) -> 9240 | F10: =SUM(F7:F9) -> 9595 | G10: =SUM(G7:G9) -> 9906 | H10: =SUM(H7:H9) -> 10182 | I10: =SUM(I7:I9) -> 10455 | J10: =SUM(J7:J9) -> 10678
B12: 売上原価（OEM仕入・資材） | C12: 3271 | D12: 3528 | E12: 3788 | F12: =ROUND(F10*inp!F37,0) -> 3934 | G12: =ROUND(G10*inp!G37,0) -> 4061 | H12: =ROUND(H10*inp!H37,0) -> 4175 | I12: =ROUND(I10*inp!I37,0) -> 4287 | J12: =ROUND(J10*inp!J37,0) -> 4378
B13: 売上総利益 | C13: =C10-C12 -> 4517 | D13: =D10-D12 -> 4972 | E13: =E10-E12 -> 5452 | F13: =F10-F12 -> 5661 | G13: =G10-G12 -> 5845 | H13: =H10-H12 -> 6007 | I13: =I10-I12 -> 6168 | J13: =J10-J12 -> 6300
B14: 売上総利益率 | C14: =C13/C10 -> 0.57999486 | D14: =D13/D10 -> 0.58494118 | E14: =E13/E10 -> 0.59004329 | F14: =F13/F10 -> 0.58999479 | G14: =G13/G10 -> 0.59004644 | H14: =H13/H10 -> 0.58996268 | I14: =I13/I10 -> 0.58995696 | J14: =J13/J10 -> 0.58999813
B16: 広告宣伝費 | C16: 1324 | D16: 1488 | E16: 1663 | F16: =ROUND(F10*inp!F38,0) -> 1727 | G16: =ROUND(G10*inp!G38,0) -> 1783 | H16: =ROUND(H10*inp!H38,0) -> 1833 | I16: =ROUND(I10*inp!I38,0) -> 1882 | J16: =ROUND(J10*inp!J38,0) -> 1922
B17: 物流費（配送・倉庫） | C17: 639 | D17: 689 | E17: 739 | F17: =ROUND(F10*inp!F39,0) -> 768 | G17: =ROUND(G10*inp!G39,0) -> 792 | H17: =ROUND(H10*inp!H39,0) -> 815 | I17: =ROUND(I10*inp!I39,0) -> 836 | J17: =ROUND(J10*inp!J39,0) -> 854
B18: 人件費 | C18: 870 | D18: 905 | E18: 950 | F18: 975 | G18: 1000 | H18: 1025 | I18: 1050 | J18: 1075
B19: その他販管費 | C19: 1050 | D19: 1096 | E19: 1140 | F19: 1165 | G19: 1190 | H19: 1215 | I19: 1240 | J19: 1265
B20: 販売費及び一般管理費 合計 | C20: =SUM(C16:C19) -> 3883 | D20: =SUM(D16:D19) -> 4178 | E20: =SUM(E16:E19) -> 4492 | F20: =SUM(F16:F19) -> 4635 | G20: =SUM(G16:G19) -> 4765 | H20: =SUM(H16:H19) -> 4888 | I20: =SUM(I16:I19) -> 5008 | J20: =SUM(J16:J19) -> 5116
B21: 営業利益（EBIT） | C21: =C13-C20 -> 634 | D21: =D13-D20 -> 794 | E21: =E13-E20 -> 960 | F21: =F13-F20 -> 1026 | G21: =G13-G20 -> 1080 | H21: =H13-H20 -> 1119 | I21: =I13-I20 -> 1160 | J21: =J13-J20 -> 1184
B22: 営業利益率 | C22: =C21/C10 -> 0.081407293 | D22: =D21/D10 -> 0.093411765 | E22: =E21/E10 -> 0.1038961 | F22: =F21/F10 -> 0.10693069 | G22: =G21/G10 -> 0.10902483 | H22: =H21/H10 -> 0.10989982 | I22: =I21/I10 -> 0.1109517 | J22: =J21/J10 -> 0.11088219
B24: 減価償却費及び償却費 | C24: 150 | D24: 155 | E24: 160 | F24: 165 | G24: 168 | H24: 171 | I24: 174 | J24: 177
B25: EBITDA | C25: =C21+C24 -> 784 | D25: =D21+D24 -> 949 | E25: =E21+E24 -> 1120 | F25: =F21+F24 -> 1191 | G25: =G21+G24 -> 1248 | H25: =H21+H24 -> 1290 | I25: =I21+I24 -> 1334 | J25: =J21+J24 -> 1361
B26: EBITDAマージン | C26: =C25/C10 -> 0.10066769 | D26: =D25/D10 -> 0.11164706 | E26: =E25/E10 -> 0.12121212 | F26: =F25/F10 -> 0.12412715 | G26: =G25/G10 -> 0.12598425 | H26: =H25/H10 -> 0.12669417 | I26: =I25/I10 -> 0.12759445 | J26: =J25/J10 -> 0.12745833
B28: 支払利息 | C28: 28 | D28: 25 | E28: 22 | F28: =debt!F12 -> 105 | G28: =debt!G12 -> 94 | H28: =debt!H12 -> 83 | I28: =debt!I12 -> 72 | J28: =debt!J12 -> 61
B29: 営業外損益（純額） | C29: 6 | D29: 7 | E29: 8 | F29: 8 | G29: 8 | H29: 8 | I29: 8 | J29: 8
B30: 経常利益 | C30: =C21-C28+C29 -> 612 | D30: =D21-D28+D29 -> 776 | E30: =E21-E28+E29 -> 946 | F30: =F21-F28+F29 -> 929 | G30: =G21-G28+G29 -> 994 | H30: =H21-H28+H29 -> 1044 | I30: =I21-I28+I29 -> 1096 | J30: =J21-J28+J29 -> 1131
B31: 法人税等（実効税率30.5%） | C31: =ROUND(C30*0.305,0) -> 187 | D31: =ROUND(D30*0.305,0) -> 237 | E31: =ROUND(E30*0.305,0) -> 289 | F31: =ROUND(F30*0.305,0) -> 283 | G31: =ROUND(G30*0.305,0) -> 303 | H31: =ROUND(H30*0.305,0) -> 318 | I31: =ROUND(I30*0.305,0) -> 334 | J31: =ROUND(J30*0.305,0) -> 345
B32: 当期純利益 | C32: =C30-C31 -> 425 | D32: =D30-D31 -> 539 | E32: =E30-E31 -> 657 | F32: =F30-F31 -> 646 | G32: =G30-G31 -> 691 | H32: =H30-H31 -> 726 | I32: =I30-I31 -> 762 | J32: =J30-J31 -> 786

Sheet BS
A1: 貸借対照表（Projected B/S）
A2: （単位：百万円） | H2: ケース: Bank Base Case
C4: 2024/3期 | D4: 2025/3期 | E4: 2026/3期 | F4: 2027/3期 | G4: 2028/3期 | H4: 2029/3期 | I4: 2030/3期 | J4: 2031/3期
C5: A（実績） | D5: A（実績） | E5: A（実績） | F5: P（計画） | G5: P（計画） | H5: P（計画） | I5: P（計画） | J5: P（計画）
B7: 現金及び現金同等物 | C7: 380 | D7: 500 | E7: 620 | F7: =CF!F21 -> 351 | G7: =CF!G21 -> 496 | H7: =CF!H21 -> 687 | I7: =CF!I21 -> 918 | J7: =CF!J21 -> 1190
B8: 営業債権（売掛金） | C8: 960 | D8: 1048 | E8: 1139 | F8: =ROUND(PL!F10*45/365,0) -> 1183 | G8: =ROUND(PL!G10*45/365,0) -> 1221 | H8: =ROUND(PL!H10*45/365,0) -> 1255 | I8: =ROUND(PL!I10*45/365,0) -> 1289 | J8: =ROUND(PL!J10*45/365,0) -> 1316
B9: 棚卸資産 | C9: 1050 | D9: 1140 | E9: 1230 | F9: =ROUND(PL!F12*118/365,0) -> 1272 | G9: =ROUND(PL!G12*118/365,0) -> 1313 | H9: =ROUND(PL!H12*118/365,0) -> 1350 | I9: =ROUND(PL!I12*118/365,0) -> 1386 | J9: =ROUND(PL!J12*118/365,0) -> 1415
B10: その他流動資産 | C10: 170 | D10: 185 | E10: 200 | F10: 205 | G10: 210 | H10: 215 | I10: 220 | J10: 225
B11: 有形固定資産 | C11: 640 | D11: 660 | E11: 680 | F11: =E11+inp!F41-PL!F24 -> 685 | G11: =F11+inp!G41-PL!G24 -> 687 | H11: =G11+inp!H41-PL!H24 -> 686 | I11: =H11+inp!I41-PL!I24 -> 682 | J11: =I11+inp!J41-PL!J24 -> 675
B12: のれん | C12: 0 | D12: 0 | E12: 0 | F12: 6100 | G12: 6100 | H12: 6100 | I12: 6100 | J12: 6100
B13: 無形固定資産・その他 | C13: 220 | D13: 235 | E13: 250 | F13: 715 | G13: 715 | H13: 715 | I13: 715 | J13: 715
B14: 資産合計 | C14: =SUM(C7:C13) -> 3420 | D14: =SUM(D7:D13) -> 3768 | E14: =SUM(E7:E13) -> 4119 | F14: =SUM(F7:F13) -> 10511 | G14: =SUM(G7:G13) -> 10742 | H14: =SUM(H7:H13) -> 11008 | I14: =SUM(I7:I13) -> 11310 | J14: =SUM(J7:J13) -> 11636
B16: 営業債務（買掛金・未払費用） | C16: 590 | D16: 640 | E16: 690 | F16: 720 | G16: 740 | H16: 760 | I16: 780 | J16: 800
B17: その他負債 | C17: 180 | D17: 198 | E17: 179 | F17: 190 | G17: 190 | H17: 190 | I17: 190 | J17: 190
B18: 有利子負債 | C18: 600 | D18: 500 | E18: 400 | F18: =debt!F9 -> 4320 | G18: =debt!G9 -> 3840 | H18: =debt!H9 -> 3360 | I18: =debt!I9 -> 2880 | J18: =debt!J9 -> 2400
B19: 負債合計 | C19: =SUM(C16:C18) -> 1370 | D19: =SUM(D16:D18) -> 1338 | E19: =SUM(E16:E18) -> 1269 | F19: =SUM(F16:F18) -> 5230 | G19: =SUM(G16:G18) -> 4770 | H19: =SUM(H16:H18) -> 4310 | I19: =SUM(I16:I18) -> 3850 | J19: =SUM(J16:J18) -> 3390
B21: 純資産 | C21: 2050 | D21: 2430 | E21: 2850 | F21: 5281 | G21: 5972 | H21: 6698 | I21: 7460 | J21: 8246
B22: 負債純資産合計 | C22: =C19+C21 -> 3420 | D22: =D19+D21 -> 3768 | E22: =E19+E21 -> 4119 | F22: =F19+F21 -> 10511 | G22: =G19+G21 -> 10742 | H22: =H19+H21 -> 11008 | I22: =I19+I21 -> 11310 | J22: =J19+J21 -> 11636
B24: ※ 2027/3期以降は買収後連結（のれん計上・買収時調整を純資産に含む）。のれんは暫定PPA前の想定額（inp参照）。

Sheet CF
A1: キャッシュフロー計算書（Projected C/F）
A2: （単位：百万円） | H2: ケース: Bank Base Case
C4: 2024/3期 | D4: 2025/3期 | E4: 2026/3期 | F4: 2027/3期 | G4: 2028/3期 | H4: 2029/3期 | I4: 2030/3期 | J4: 2031/3期
C5: A（実績） | D5: A（実績） | E5: A（実績） | F5: P（計画） | G5: P（計画） | H5: P（計画） | I5: P（計画） | J5: P（計画）
B7: 税引後当期純利益 | C7: =PL!C32 -> 425 | D7: =PL!D32 -> 539 | E7: =PL!E32 -> 657 | F7: =PL!F32 -> 646 | G7: =PL!G32 -> 691 | H7: =PL!H32 -> 726 | I7: =PL!I32 -> 762 | J7: =PL!J32 -> 786
B8: 減価償却費及び償却費 | C8: =PL!C24 -> 150 | D8: =PL!D24 -> 155 | E8: =PL!E24 -> 160 | F8: =PL!F24 -> 165 | G8: =PL!G24 -> 168 | H8: =PL!H24 -> 171 | I8: =PL!I24 -> 174 | J8: =PL!J24 -> 177
B9: 運転資本増減・その他（△増加） | C9: 145 | D9: 116 | E9: 88 | F9: -50 | G9: -64 | H9: -56 | I9: -55 | J9: -41
B10: 営業キャッシュフロー | C10: =SUM(C7:C9) -> 720 | D10: =SUM(D7:D9) -> 810 | E10: =SUM(E7:E9) -> 905 | F10: =SUM(F7:F9) -> 761 | G10: =SUM(G7:G9) -> 795 | H10: =SUM(H7:H9) -> 841 | I10: =SUM(I7:I9) -> 881 | J10: =SUM(J7:J9) -> 922
B12: 設備投資等（投資CF） | C12: -140 | D12: -150 | E12: -160 | F12: =-inp!F41 -> -170 | G12: =-inp!G41 -> -170 | H12: =-inp!H41 -> -170 | I12: =-inp!I41 -> -170 | J12: =-inp!J41 -> -170
B13: フリー・キャッシュフロー（FCF） | C13: =C10+C12 -> 580 | D13: =D10+D12 -> 660 | E13: =E10+E12 -> 745 | F13: =F10+F12 -> 591 | G13: =G10+G12 -> 625 | H13: =H10+H12 -> 671 | I13: =I10+I12 -> 711 | J13: =J10+J12 -> 752
B15: 借入金返済 | C15: -100 | D15: -100 | E15: -100 | F15: =-debt!F8 -> -480 | G15: =-debt!G8 -> -480 | H15: =-debt!H8 -> -480 | I15: =-debt!I8 -> -480 | J15: =-debt!J8 -> -480
B16: 配当・その他財務 | C16: -420 | D16: -440 | E16: -525 | F16: 0 | G16: 0 | H16: 0 | I16: 0 | J16: 0
B17: 財務キャッシュフロー | C17: =C15+C16 -> -520 | D17: =D15+D16 -> -540 | E17: =E15+E16 -> -625 | F17: =F15+F16 -> -480 | G17: =G15+G16 -> -480 | H17: =H15+H16 -> -480 | I17: =I15+I16 -> -480 | J17: =J15+J16 -> -480
B19: 現金増減 | C19: =C13+C17 -> 60 | D19: =D13+D17 -> 120 | E19: =E13+E17 -> 120 | F19: =F13+F17 -> 111 | G19: =G13+G17 -> 145 | H19: =H13+H17 -> 191 | I19: =I13+I17 -> 231 | J19: =J13+J17 -> 272
B20: 期首現金 | C20: 320 | D20: =C21 -> 380 | E20: =D21 -> 500 | F20: 240 | G20: =F21 -> 351 | H20: =G21 -> 496 | I20: =H21 -> 687 | J20: =I21 -> 918
B21: 期末現金 | C21: =C19+C20 -> 380 | D21: =D19+D20 -> 500 | E21: =E19+E20 -> 620 | F21: =F19+F20 -> 351 | G21: =G19+G20 -> 496 | H21: =H19+H20 -> 687 | I21: =I19+I20 -> 918 | J21: =J19+J20 -> 1190
B24: ※ 2027/3期期首現金は買収時調整後（手元現金380百万円を買収資金に充当後の240百万円）。

Sheet debt
A1: デットスケジュール（シニアタームローンA）
A2: （単位：百万円） | H2: ケース: Bank Base Case
C4: 2024/3期 | D4: 2025/3期 | E4: 2026/3期 | F4: 2027/3期 | G4: 2028/3期 | H4: 2029/3期 | I4: 2030/3期 | J4: 2031/3期
C5: A（実績） | D5: A（実績） | E5: A（実績） | F5: P（計画） | G5: P（計画） | H5: P（計画） | I5: P（計画） | J5: P（計画）
B7: 期初残高 | F7: =inp!D11 -> 4800 | G7: =F9 -> 4320 | H7: =G9 -> 3840 | I7: =H9 -> 3360 | J7: =I9 -> 2880
B8: 約定弁済 | F8: =inp!D19 -> 480 | G8: =inp!D19 -> 480 | H8: =inp!D19 -> 480 | I8: =inp!D19 -> 480 | J8: =inp!D19 -> 480
B9: 期末残高 | F9: =F7-F8 -> 4320 | G9: =G7-G8 -> 3840 | H9: =H7-H8 -> 3360 | I9: =I7-I8 -> 2880 | J9: =J7-J8 -> 2400
B10: 平均残高 | F10: =(F7+F9)/2 -> 4560 | G10: =(G7+G9)/2 -> 4080 | H10: =(H7+H9)/2 -> 3600 | I10: =(I7+I9)/2 -> 3120 | J10: =(J7+J9)/2 -> 2640
B11: 適用金利（TIBOR+230bp想定） | F11: =inp!D18 -> 0.023 | G11: =inp!D18 -> 0.023 | H11: =inp!D18 -> 0.023 | I11: =inp!D18 -> 0.023 | J11: =inp!D18 -> 0.023
B12: 支払利息 | F12: =ROUND(F10*F11,0) -> 105 | G12: =ROUND(G10*G11,0) -> 94 | H12: =ROUND(H10*H11,0) -> 83 | I12: =ROUND(I10*I11,0) -> 72 | J12: =ROUND(J10*J11,0) -> 61
B14: ※ 約定弁済は年480百万円、最終回（FY34）残額一括。実績年欄は対象外（既存借入はBS参照）。

Sheet memo
A1: （作業メモ・成果物ではありません）
B3: 6/18 銀行提出用に単位を百万円へ統一（旧版は千円）
B4: TODO: PPA確定後にのれん・無形の内訳を更新（暫定 6,100 / 465）
B5: リピート率の定義＝当期購入会員のうち前期も購入した会員の比率（CRM抽出）
B6: 卸の店販は帳合経由の出荷ベース。返品控除後
