Workbook

Sheet Cover
B4: Project Gear
B6: 株式会社オートスタッフ中部 財務モデル
B8: ケース：Base Case（ベースケース）
B10: 作成：日本橋キャピタルパートナーズ株式会社
B11: 作成日：2026年7月10日（Ver. 3.4・12期拡張版）
B13: 【取扱厳重注意】
B14: 本資料は貴行における本件検討のためにのみ作成されたものであり、作成者の事前の書面による同意なく第三者への開示・複製を禁じます。
B15: 本資料に含まれる将来予測は多くの前提・仮定に基づくものであり、その実現性を保証するものではありません。

Sheet Assumptions
A1: 前提条件（Assumptions）
A2: （単位：千円） | E2: ケース: Base Case
C4: FY22 | D4: FY23 | E4: FY24 | F4: FY25 | G4: FY26 | H4: FY27 | I4: FY28 | J4: FY29 | K4: FY30 | L4: FY31 | M4: FY32 | N4: FY33
C5: 実績 | D5: 実績 | E5: 実績 | F5: 実績 | G5: 実績 | H5: 計画 | I5: 計画 | J5: 計画 | K5: 計画 | L5: 計画 | M5: 計画 | N5: 計画
B6: オペレーティング前提（年度別）
B7: 稼働率（Utilization） | C7: =KPI_Drivers!C8 | D7: =KPI_Drivers!D8 | E7: =KPI_Drivers!E8 | F7: =KPI_Drivers!F8 | G7: =KPI_Drivers!G8 | H7: =KPI_Drivers!H8 | I7: =KPI_Drivers!I8 | J7: =KPI_Drivers!J8 | ... N7: =KPI_Drivers!N8
B8: 派遣単価（円/h） | C8: =KPI_Drivers!C11 | D8: =KPI_Drivers!D11 | E8: =KPI_Drivers!E11 | F8: =KPI_Drivers!F11 | G8: =KPI_Drivers!G11 | H8: =KPI_Drivers!H11 | I8: =KPI_Drivers!I11 | J8: =KPI_Drivers!J11 | ... N8: =KPI_Drivers!N11
B9: 採用単価（CPA・千円/名） | C9: =KPI_Drivers!C15 | D9: =KPI_Drivers!D15 | E9: =KPI_Drivers!E15 | F9: =KPI_Drivers!F15 | G9: =KPI_Drivers!G15 | H9: =KPI_Drivers!H15 | I9: =KPI_Drivers!I15 | J9: =KPI_Drivers!J15 | ... N9: =KPI_Drivers!N15
B10: 新規採用人数（名） | C10: =KPI_Drivers!C14 | D10: =KPI_Drivers!D14 | E10: =KPI_Drivers!E14 | F10: =KPI_Drivers!F14 | G10: =KPI_Drivers!G14 | H10: =KPI_Drivers!H14 | I10: =KPI_Drivers!I14 | J10: =KPI_Drivers!J14 | ... N10: =KPI_Drivers!N14
B12: ストラクチャー（千円）
B13: エンタープライズ・バリュー（EV） | D13: 12000000
B14: エクイティ出資 | D14: 5500000
B15: シニアローン総額 | D15: 6500000
B16: うち参加金融機関A行 想定取組額 | D16: 2500000
B17: ローン期間（年） | D17: 7
B18: 適用金利（TIBOR+200bp想定） | D18: 0.022
B19: 約定弁済（年・最終回残額一括） | D19: 650000
B20: クローズ想定 | D20: 2026年9月末
B21: のれん想定額（暫定PPA前） | D21: 5500000
B23: その他前提
B24: 実効税率 | D24: 0.31
B25: 売上債権回転日数 | D25: 45
B26: 買収時現金調整（取引費用等） | D26: -750000

Sheet PL
A1: 損益計算書（Projected P&L）
E2: ケース: Base Case | N2: 単位:千円
C4: FY22 | D4: FY23 | E4: FY24 | F4: FY25 | G4: FY26 | H4: FY27 | I4: FY28 | J4: FY29 | K4: FY30 | L4: FY31 | M4: FY32 | N4: FY33
C5: 実績 | D5: 実績 | E5: 実績 | F5: 実績 | G5: 実績 | H5: 計画 | I5: 計画 | J5: 計画 | K5: 計画 | L5: 計画 | M5: 計画 | N5: 計画
B7: 派遣事業売上 | C7: 10929485 | D7: 11669061 | E7: 12314768 | F7: 13205127 | G7: 13988621 | H7: =ROUND(KPI_Drivers!H9*KPI_Drivers!H10*KPI_Drivers!H11*12/1000,0) | I7: =ROUND(KPI_Drivers!I9*KPI_Drivers!I10*KPI_Drivers!I11*12/1000,0) | J7: =ROUND(KPI_Drivers!J9*KPI_Drivers!J10*KPI_Drivers!J11*12/1000,0) | K7: =ROUND(KPI_Drivers!K9*KPI_Drivers!K10*KPI_Drivers!K11*12/1000,0) | L7: =ROUND(KPI_Drivers!L9*KPI_Drivers!L10*KPI_Drivers!L11*12/1000,0) | M7: =ROUND(KPI_Drivers!M9*KPI_Drivers!M10*KPI_Drivers!M11*12/1000,0) | N7: =ROUND(KPI_Drivers!N9*KPI_Drivers!N10*KPI_Drivers!N11*12/1000,0)
B8: その他営業収入（紹介手数料等） | C8: 130000 | D8: 138000 | E8: 145232 | F8: 158000 | G8: 171379 | H8: 176092 | I8: 180000 | J8: 184000 | K8: 188000 | L8: 192000 | M8: 196000 | N8: 200000
B9: 売上高（Net Sales） | C9: =SUM(C7:C8) | D9: =SUM(D7:D8) | E9: =SUM(E7:E8) | F9: =SUM(F7:F8) | G9: =SUM(G7:G8) | H9: =SUM(H7:H8) | I9: =SUM(I7:I8) | J9: =SUM(J7:J8) | ... N9: =SUM(N7:N8)
B11: スタッフ労務費（法定福利費込） | C11: 8625886 | D11: 9214737 | E11: 9729886 | F11: 10413461 | G11: 11011043 | H11: =ROUND(KPI_Drivers!H9*KPI_Drivers!H10*KPI_Drivers!H12*(1+KPI_Drivers!H13)*12/1000,0) | I11: =ROUND(KPI_Drivers!I9*KPI_Drivers!I10*KPI_Drivers!I12*(1+KPI_Drivers!I13)*12/1000,0) | J11: =ROUND(KPI_Drivers!J9*KPI_Drivers!J10*KPI_Drivers!J12*(1+KPI_Drivers!J13)*12/1000,0) | K11: =ROUND(KPI_Drivers!K9*KPI_Drivers!K10*KPI_Drivers!K12*(1+KPI_Drivers!K13)*12/1000,0) | L11: =ROUND(KPI_Drivers!L9*KPI_Drivers!L10*KPI_Drivers!L12*(1+KPI_Drivers!L13)*12/1000,0) | M11: =ROUND(KPI_Drivers!M9*KPI_Drivers!M10*KPI_Drivers!M12*(1+KPI_Drivers!M13)*12/1000,0) | N11: =ROUND(KPI_Drivers!N9*KPI_Drivers!N10*KPI_Drivers!N12*(1+KPI_Drivers!N13)*12/1000,0)
B12: その他売上原価 | C12: 265000 | D12: 272000 | E12: 282000 | F12: 290000 | G12: 300000 | H12: 310000 | I12: 318000 | J12: 326000 | K12: 334000 | L12: 342000 | M12: 350000 | N12: 358000
B13: 売上原価 合計 | C13: =C11+C12 | D13: =D11+D12 | E13: =E11+E12 | F13: =F11+F12 | G13: =G11+G12 | H13: =H11+H12 | I13: =I11+I12 | J13: =J11+J12 | ... N13: =N11+N12
B14: 売上総利益 | C14: =C9-C13 | D14: =D9-D13 | E14: =E9-E13 | F14: =F9-F13 | G14: =G9-G13 | H14: =H9-H13 | I14: =I9-I13 | J14: =J9-J13 | ... N14: =N9-N13
B15: 売上総利益率 | C15: =C14/C9 | D15: =D14/D9 | E15: =E14/E9 | F15: =F14/F9 | G15: =G14/G9 | H15: =H14/H9 | I15: =I14/I9 | J15: =J14/J9 | ... N15: =N14/N9
B17: 採用費 | C17: 188600 | D17: 210700 | E17: 236250 | F17: 266560 | G17: 295000 | H17: =KPI_Drivers!H14*KPI_Drivers!H15 | I17: =KPI_Drivers!I14*KPI_Drivers!I15 | J17: =KPI_Drivers!J14*KPI_Drivers!J15 | K17: =KPI_Drivers!K14*KPI_Drivers!K15 | L17: =KPI_Drivers!L14*KPI_Drivers!L15 | M17: =KPI_Drivers!M14*KPI_Drivers!M15 | N17: =KPI_Drivers!N14*KPI_Drivers!N15
B18: 本社人件費 | C18: 555000 | D18: 570000 | E18: 585000 | F18: 600000 | G18: 620000 | H18: 640000 | I18: 652000 | J18: 664000 | K18: 676000 | L18: 688000 | M18: 700000 | N18: 712000
B19: その他販管費 | C19: 385000 | D19: 391000 | E19: 398000 | F19: 405000 | G19: 419000 | H19: 428507 | I19: 433000 | J19: 437500 | K19: 442000 | L19: 446500 | M19: 451000 | N19: 455500
B20: 販売費及び一般管理費 合計 | C20: =SUM(C17:C19) | D20: =SUM(D17:D19) | E20: =SUM(E17:E19) | F20: =SUM(F17:F19) | G20: =SUM(G17:G19) | H20: =SUM(H17:H19) | I20: =SUM(I17:I19) | J20: =SUM(J17:J19) | ... N20: =SUM(N17:N19)
B21: 営業利益（Operating Profit） | C21: =C14-C20 | D21: =D14-D20 | E21: =E14-E20 | F21: =F14-F20 | G21: =G14-G20 | H21: =H14-H20 | I21: =I14-I20 | J21: =J14-J20 | ... N21: =N14-N20
B22: 営業利益率 | C22: =C21/C9 | D22: =D21/D9 | E22: =E21/E9 | F22: =F21/F9 | G22: =G21/G9 | H22: =H21/H9 | I22: =I21/I9 | J22: =J21/J9 | ... N22: =N21/N9
B24: 減価償却費 | C24: 84000 | D24: 88000 | E24: 92000 | F24: 98000 | G24: 105043 | H24: 113700 | I24: 115700 | J24: 117700 | K24: 119700 | L24: 121700 | M24: 123700 | N24: 125700
B25: Adj. EBITDA | C25: =C21+C24 | D25: =D21+D24 | E25: =E21+E24 | F25: =F21+F24 | G25: =G21+G24 | H25: =H21+H24 | I25: =I21+I24 | J25: =J21+J24 | ... N25: =N21+N24
B26: EBITDAマージン | C26: =C25/C9 | D26: =D25/D9 | E26: =E25/E9 | F26: =F25/F9 | G26: =G25/G9 | H26: =H25/H9 | I26: =I25/I9 | J26: =J25/J9 | ... N26: =N25/N9
B28: 支払利息 | C28: 16000 | D28: 15000 | E28: 14000 | F28: 13000 | G28: 12000 | H28: =Debt_Schedule!H12 | I28: =Debt_Schedule!I12 | J28: =Debt_Schedule!J12 | K28: =Debt_Schedule!K12 | L28: =Debt_Schedule!L12 | M28: =Debt_Schedule!M12 | N28: =Debt_Schedule!N12
B29: 営業外損益（純額） | C29: 4200 | D29: 4500 | E29: 4800 | F29: 5200 | G29: 5500 | H29: 6000 | I29: 6000 | J29: 6000 | K29: 6000 | L29: 6000 | M29: 6000 | N29: 6000
B30: 経常利益 | C30: =C21-C28+C29 | D30: =D21-D28+D29 | E30: =E21-E28+E29 | F30: =F21-F28+F29 | G30: =G21-G28+G29 | H30: =H21-H28+H29 | I30: =I21-I28+I29 | J30: =J21-J28+J29 | ... N30: =N21-N28+N29
B31: 法人税等（実効税率31%） | C31: =ROUND(C30*0.31,0) | D31: =ROUND(D30*0.31,0) | E31: =ROUND(E30*0.31,0) | F31: =ROUND(F30*0.31,0) | G31: =ROUND(G30*0.31,0) | H31: =ROUND(H30*0.31,0) | I31: =ROUND(I30*0.31,0) | J31: =ROUND(J30*0.31,0) | ... N31: =ROUND(N30*0.31,0)
B32: 当期純利益 | C32: =C30-C31 | D32: =D30-D31 | E32: =E30-E31 | F32: =F30-F31 | G32: =G30-G31 | H32: =H30-H31 | I32: =I30-I31 | J32: =J30-J31 | ... N32: =N30-N31

Sheet BS
A1: 貸借対照表（Projected B/S）
A2: （単位：千円） | E2: ケース: Base Case
C4: FY22 | D4: FY23 | E4: FY24 | F4: FY25 | G4: FY26 | H4: FY27 | I4: FY28 | J4: FY29 | K4: FY30 | L4: FY31 | M4: FY32 | N4: FY33
C5: 実績 | D5: 実績 | E5: 実績 | F5: 実績 | G5: 実績 | H5: 計画 | I5: 計画 | J5: 計画 | K5: 計画 | L5: 計画 | M5: 計画 | N5: 計画
B7: 現金及び預金 | C7: 1150000 | D7: 1300000 | E7: 1420000 | F7: 1640000 | G7: 1850000 | H7: 1457150 | I7: 1860969 | J7: 2335018 | K7: 2883007 | L7: 3506456 | M7: 4206521 | N7: 3049823
B8: 売上債権 | C8: 1365000 | D8: 1455000 | E8: 1540000 | F8: 1650000 | G8: 1750000 | H8: 1836000 | I8: 1905000 | J8: 1973000 | K8: 2043000 | L8: 2114000 | M8: 2186000 | N8: 2259000
B9: その他流動資産 | C9: 160000 | D9: 170000 | E9: 180000 | F9: 190000 | G9: 200000 | H9: 210000 | I9: 215000 | J9: 220000 | K9: 225000 | L9: 230000 | M9: 235000 | N9: 240000
B10: 流動資産 合計 | C10: =SUM(C7:C9) | D10: =SUM(D7:D9) | E10: =SUM(E7:E9) | F10: =SUM(F7:F9) | G10: =SUM(G7:G9) | H10: =SUM(H7:H9) | I10: =SUM(I7:I9) | J10: =SUM(J7:J9) | ... N10: =SUM(N7:N9)
B12: 有形固定資産 | C12: 780000 | D12: 800000 | E12: 820000 | F12: 840000 | G12: 860000 | H12: 866300 | I12: 870600 | J12: 872900 | K12: 873200 | L12: 871500 | M12: 867800 | N12: 862100
B13: のれん（Goodwill） | C13: 0 | D13: 0 | E13: 0 | F13: 0 | G13: 0 | H13: 5500000 | I13: 5500000 | J13: 5500000 | K13: 5500000 | L13: 5500000 | M13: 5500000 | N13: 5500000
B14: 無形固定資産・その他 | C14: 240000 | D14: 250000 | E14: 260000 | F14: 270000 | G14: 280000 | H14: 290000 | I14: 290000 | J14: 290000 | K14: 290000 | L14: 290000 | M14: 290000 | N14: 290000
B15: 固定資産 合計 | C15: =SUM(C12:C14) | D15: =SUM(D12:D14) | E15: =SUM(E12:E14) | F15: =SUM(F12:F14) | G15: =SUM(G12:G14) | H15: =SUM(H12:H14) | I15: =SUM(I12:I14) | J15: =SUM(J12:J14) | ... N15: =SUM(N12:N14)
B16: 資産合計 | C16: =C10+C15 | D16: =D10+D15 | E16: =E10+E15 | F16: =F10+F15 | G16: =G10+G15 | H16: =H10+H15 | I16: =I10+I15 | J16: =J10+J15 | ... N16: =N10+N15
B18: 仕入債務・未払費用 | C18: 980000 | D18: 1030000 | E18: 1080000 | F18: 1130000 | G18: 1180000 | H18: 1240000 | I18: 1265000 | J18: 1290000 | K18: 1315000 | L18: 1340000 | M18: 1365000 | N18: 1390000
B19: その他負債 | C19: 1270000 | D19: 1030000 | E19: 790000 | F19: 550000 | G19: 310000 | H19: 320000 | I19: 320000 | J19: 320000 | K19: 320000 | L19: 320000 | M19: 320000 | N19: 320000
B20: 有利子負債 | C20: 500000 | D20: 450000 | E20: 400000 | F20: 350000 | G20: 300000 | H20: =Debt_Schedule!H9 | I20: =Debt_Schedule!I9 | J20: =Debt_Schedule!J9 | K20: =Debt_Schedule!K9 | L20: =Debt_Schedule!L9 | M20: =Debt_Schedule!M9 | N20: =Debt_Schedule!N9
B21: 負債合計 | C21: =SUM(C18:C20) | D21: =SUM(D18:D20) | E21: =SUM(E18:E20) | F21: =SUM(F18:F20) | G21: =SUM(G18:G20) | H21: =SUM(H18:H20) | I21: =SUM(I18:I20) | J21: =SUM(J18:J20) | ... N21: =SUM(N18:N20)
B23: 純資産（Net Assets） | C23: 945000 | D23: 1465000 | E23: 1950000 | F23: 2560000 | G23: 3150000 | H23: 2749450 | I23: 3856569 | J23: 5030918 | K23: 6279207 | L23: 7601956 | M23: 9000321 | N23: 10490923
B24: 負債純資産合計 | C24: =C21+C23 | D24: =D21+D23 | E24: =E21+E23 | F24: =F21+F23 | G24: =G21+G23 | H24: =H21+H23 | I24: =I21+I23 | J24: =J21+J23 | ... N24: =N21+N23
B26: ※ FY27以降は買収後連結（のれん計上・買収時調整を純資産に含む）。のれんは暫定PPA前の想定額。

Sheet CF
A1: キャッシュフロー計算書（Projected C/F・千円）
E2: ケース: Base Case
C4: FY22 | D4: FY23 | E4: FY24 | F4: FY25 | G4: FY26 | H4: FY27 | I4: FY28 | J4: FY29 | K4: FY30 | L4: FY31 | M4: FY32 | N4: FY33
C5: 実績 | D5: 実績 | E5: 実績 | F5: 実績 | G5: 実績 | H5: 計画 | I5: 計画 | J5: 計画 | K5: 計画 | L5: 計画 | M5: 計画 | N5: 計画
B7: 税引後当期純利益 | C7: =PL!C32 | D7: =PL!D32 | E7: =PL!E32 | F7: =PL!F32 | G7: =PL!G32 | H7: =PL!H32 | I7: =PL!I32 | J7: =PL!J32 | ... N7: =PL!N32
B8: 減価償却費 | C8: =PL!C24 | D8: =PL!D24 | E8: =PL!E24 | F8: =PL!F24 | G8: =PL!G24 | H8: =PL!H24 | I8: =PL!I24 | J8: =PL!J24 | ... N8: =PL!N24
B9: 運転資本増減・その他（△増加） | C9: 186543 | D9: 191694 | E9: 216432 | F9: 239589 | G9: 274122 | H9: -36000 | I9: -49000 | J9: -48000 | K9: -50000 | L9: -51000 | M9: -52000 | N9: -53000
B10: 営業キャッシュフロー | C10: =SUM(C7:C9) | D10: =SUM(D7:D9) | E10: =SUM(E7:E9) | F10: =SUM(F7:F9) | G10: =SUM(G7:G9) | H10: =SUM(H7:H9) | I10: =SUM(I7:I9) | J10: =SUM(J7:J9) | ... N10: =SUM(N7:N9)
B12: 設備投資等（投資CF） | C12: -90000 | D12: -95000 | E12: -100000 | F12: -110000 | G12: -115000 | H12: -120000 | I12: -120000 | J12: -120000 | K12: -120000 | L12: -120000 | M12: -120000 | N12: -120000
B13: フリー・キャッシュフロー（FCF） | C13: =C10+C12 | D13: =D10+D12 | E13: =E10+E12 | F13: =F10+F12 | G13: =G10+G12 | H13: =H10+H12 | I13: =I10+I12 | J13: =J10+J12 | ... N13: =N10+N12
B15: 借入金返済 | C15: -50000 | D15: -50000 | E15: -50000 | F15: -50000 | G15: -50000 | H15: =-Debt_Schedule!H8 | I15: =-Debt_Schedule!I8 | J15: =-Debt_Schedule!J8 | K15: =-Debt_Schedule!K8 | L15: =-Debt_Schedule!L8 | M15: =-Debt_Schedule!M8 | N15: =-Debt_Schedule!N8
B16: 配当・その他財務 | C16: -710000 | D16: -770000 | E16: -880000 | F16: -910000 | G16: -1045000 | H16: 10000 | I16: 0 | J16: 0 | K16: 0 | L16: 0 | M16: 0 | N16: 0
B17: 財務キャッシュフロー | C17: =C15+C16 | D17: =D15+D16 | E17: =E15+E16 | F17: =F15+F16 | G17: =G15+G16 | H17: =H15+H16 | I17: =I15+I16 | J17: =J15+J16 | ... N17: =N15+N16
B19: 現金増減 | C19: =C13+C17 | D19: =D13+D17 | E19: =E13+E17 | F19: =F13+F17 | G19: =G13+G17 | H19: =H13+H17 | I19: =I13+I17 | J19: =J13+J17 | ... N19: =N13+N17
B20: 期首現金 | C20: 1020000 | D20: =C21 | E20: =D21 | F20: =E21 | G20: =F21 | H20: 1100000 | I20: =H21 | J20: =I21 | K20: =J21 | L20: =K21 | M20: =L21 | N20: =M21
B21: 期末現金 | C21: =C19+C20 | D21: =D19+D20 | E21: =E19+E20 | F21: =F19+F20 | G21: =G19+G20 | H21: =H19+H20 | I21: =I19+I20 | J21: =J19+J20 | ... N21: =N19+N20
B24: ※ FY27期首現金は買収時調整後（取引費用等750,000千円控除後）。

Sheet KPI_Drivers
A1: KPIドライバー（Operating Assumptions）
A2: （単位：名・時間・円・％） | E2: ケース: Base Case
C4: FY22 | D4: FY23 | E4: FY24 | F4: FY25 | G4: FY26 | H4: FY27 | I4: FY28 | J4: FY29 | K4: FY30 | L4: FY31 | M4: FY32 | N4: FY33
C5: 実績 | D5: 実績 | E5: 実績 | F5: 実績 | G5: 実績 | H5: 計画 | I5: 計画 | J5: 計画 | K5: 計画 | L5: 計画 | M5: 計画 | N5: 計画
B7: 在籍登録スタッフ数（名） | C7: 3350 | D7: 3460 | E7: 3560 | F7: 3690 | G7: 3800 | H7: 3950 | I7: 4060 | J7: 4165 | K7: 4270 | L7: 4375 | M7: 4480 | N7: 4585
B8: 稼働率（Utilization） | C8: 0.85 | D8: 0.858 | E8: 0.865 | F8: 0.872 | G8: 0.88 | H8: 0.88 | I8: 0.88 | J8: 0.88 | K8: 0.88 | L8: 0.88 | M8: 0.88 | N8: 0.88
B9: 稼働人数（名） | C9: =ROUND(C7*C8,0) | D9: =ROUND(D7*D8,0) | E9: =ROUND(E7*E8,0) | F9: =ROUND(F7*F8,0) | G9: =ROUND(G7*G8,0) | H9: =ROUND(H7*H8,0) | I9: =ROUND(I7*I8,0) | J9: =ROUND(J7*J8,0) | ... N9: =ROUND(N7*N8,0)
B10: 月間平均稼働時間（h/名） | C10: 164 | D10: 165 | E10: 165 | F10: 166 | G10: 166 | H10: 166 | I10: 166 | J10: 166 | K10: 166 | L10: 166 | M10: 166 | N10: 166
B11: 派遣単価（円/h） | C11: 1950 | D11: 1985 | E11: 2020 | F11: 2060 | G11: 2100 | H11: 2125 | I11: 2146 | J11: 2167 | K11: 2189 | L11: 2211 | M11: 2233 | N11: 2255
B12: スタッフ平均時給（円/h） | C12: 1350 | D12: 1375 | E12: 1400 | F12: 1425 | G12: 1450 | H12: 1465 | I12: 1480 | J12: 1495 | K12: 1510 | L12: 1525 | M12: 1540 | N12: 1555
B13: 法定福利費率 | C13: 0.14 | D13: 0.14 | E13: 0.14 | F13: 0.14 | G13: 0.14 | H13: 0.14 | I13: 0.14 | J13: 0.14 | K13: 0.14 | L13: 0.14 | M13: 0.14 | N13: 0.14
B14: 新規採用人数（名） | C14: 920 | D14: 980 | E14: 1050 | F14: 1120 | G14: 1180 | H14: 1220 | I14: 1240 | J14: 1255 | K14: 1270 | L14: 1285 | M14: 1300 | N14: 1315
B15: 採用単価（CPA・千円/名） | C15: 205 | D15: 215 | E15: 225 | F15: 238 | G15: 250 | H15: 255 | I15: 260 | J15: 264 | K15: 268 | L15: 272 | M15: 276 | N15: 280
B16: 離職率（年間） | C16: 0.25 | D16: 0.245 | E16: 0.24 | F16: 0.23 | G16: 0.22 | H16: 0.22 | I16: 0.215 | J16: 0.21 | K16: 0.21 | L16: 0.205 | M16: 0.205 | N16: 0.2
B18: ※ 稼働人数 = 在籍登録スタッフ数 × 稼働率（四捨五入）

Sheet Debt_Schedule
A1: Debt Schedule (Senior Loan)
A2: (Unit: JPY thousands) | E2: Case: Base Case
C4: FY22 | D4: FY23 | E4: FY24 | F4: FY25 | G4: FY26 | H4: FY27 | I4: FY28 | J4: FY29 | K4: FY30 | L4: FY31 | M4: FY32 | N4: FY33
C5: 実績 | D5: 実績 | E5: 実績 | F5: 実績 | G5: 実績 | H5: 計画 | I5: 計画 | J5: 計画 | K5: 計画 | L5: 計画 | M5: 計画 | N5: 計画
B7: Beginning Balance | H7: 6500000 | I7: =H9 | J7: =I9 | K7: =J9 | L7: =K9 | M7: =L9 | N7: =M9
B8: Mandatory Amortization | H8: 650000 | I8: 650000 | J8: 650000 | K8: 650000 | L8: 650000 | M8: 650000 | N8: =N7
B9: Ending Balance | H9: =H7-H8 | I9: =I7-I8 | J9: =J7-J8 | K9: =K7-K8 | L9: =L7-L8 | M9: =M7-M8 | N9: =N7-N8
B10: Average Balance | H10: =(H7+H9)/2 | I10: =(I7+I9)/2 | J10: =(J7+J9)/2 | K10: =(K7+K9)/2 | L10: =(L7+L9)/2 | M10: =(M7+M9)/2 | N10: =(N7+N9)/2
B11: Interest Rate (TIBOR+200bp) | H11: 0.022 | I11: 0.022 | J11: 0.022 | K11: 0.022 | L11: 0.022 | M11: 0.022 | N11: 0.022
B12: Interest Expense | H12: =ROUND(H10*H11,0) | I12: =ROUND(I10*I11,0) | J12: =ROUND(J10*J11,0) | K12: =ROUND(K10*K11,0) | L12: =ROUND(L10*L11,0) | M12: =ROUND(M10*M11,0) | N12: =ROUND(N10*N11,0)
B14: Note: Annual mandatory amortization of JPY 650,000 thousand; bullet repayment of the remaining balance in FY33.

Sheet 月次試算表_FY26
A1: 月次試算表_FY26（2025年4月～2026年3月）
A2: （単位：円）
C4: 2025/04 | D4: 2025/05 | E4: 2025/06 | F4: 2025/07 | G4: 2025/08 | H4: 2025/09 | I4: 2025/10 | J4: 2025/11 | K4: 2025/12 | L4: 2026/01 | M4: 2026/02 | N4: 2026/03 | O4: 年度計
B7: 売上高 | C7: 1204290000 | D7: 1127522000 | E7: 1195893000 | F7: 1201891000 | G7: 1121525000 | H7: 1194694000 | I7: 1205489000 | J7: 1197093000 | K7: 1203090000 | L7: 1115527000 | M7: 1193494000 | N7: 1199492000 | O7: =SUM(C7:N7)
B8: 売上原価 | C8: 961990000 | D8: 900668000 | E8: 955282000 | F8: 960073000 | G8: 895877000 | H8: 954324000 | I8: 962948000 | J8: 956241000 | K8: 961031000 | L8: 891086000 | M8: 953366000 | N8: 958157000 | O8: =SUM(C8:N8)
B9: 売上総利益 | C9: =C7-C8 | D9: =D7-D8 | E9: =E7-E8 | F9: =F7-F8 | G9: =G7-G8 | H9: =H7-H8 | I9: =I7-I8 | J9: =J7-J8 | ... N9: =N7-N8 | O9: =SUM(C9:N9)
B10: 販売費及び一般管理費 | C10: 117837000 | D10: 108943000 | E10: 110055000 | F10: 111167000 | G10: 107832000 | H10: 110611000 | I10: 116725000 | J10: 110611000 | K10: 111722000 | L10: 108388000 | M10: 109499000 | N10: 110610000 | O10: =SUM(C10:N10)
B11: 営業利益 | C11: =C9-C10 | D11: =D9-D10 | E11: =E9-E10 | F11: =F9-F10 | G11: =G9-G10 | H11: =H9-H10 | I11: =I9-I10 | J11: =J9-J10 | ... N11: =N9-N10 | O11: =SUM(C11:N11)
B13: 現金及び預金 | C13: 1658700000 | D13: 1674200000 | E13: 1694500000 | F13: 1708500000 | G13: 1728100000 | H13: 1743200000 | I13: 1763900000 | J13: 1779500000 | K13: 1798400000 | L13: 1813800000 | M13: 1833200000 | N13: 1850000000
B14: 売上債権 | C14: 1782349000 | D14: 1668733000 | E14: 1769922000 | F14: 1778799000 | G14: 1659857000 | H14: 1768147000 | I14: 1784124000 | J14: 1771698000 | K14: 1780573000 | L14: 1650980000 | M14: 1766371000 | N14: 1750000000
B15: 仕入債務・未払費用 | C15: 1133687000 | D15: 1138653000 | E15: 1141700000 | F15: 1147267000 | G15: 1150593000 | H15: 1155720000 | I15: 1158607000 | J15: 1163533000 | K15: 1167140000 | L15: 1172147000 | M15: 1175553000 | N15: 1180000000
B17: ※ 勤怠・請求データより作成（税理士法人巡回監査済）。
