Workbook

Sheet Cover
B4: Project Gear
B6: 株式会社オートスタッフ中部 財務モデル
B8: ケース：Sponsor Case（スポンサーケース）
B10: 作成：日本橋キャピタルパートナーズ株式会社
B11: 作成日：2026年6月30日（Ver. 3.2）
B13: 【取扱厳重注意】
B14: 本資料は貴行における本件検討のためにのみ作成されたものであり、作成者の事前の書面による同意なく第三者への開示・複製を禁じます。
B15: 本資料に含まれる将来予測は多くの前提・仮定に基づくものであり、その実現性を保証するものではありません。

Sheet Assumptions
A1: 前提条件（Assumptions）
A2: （単位：千円） | H2: ケース: Sponsor Case
C4: FY24 | D4: FY25 | E4: FY26 | F4: FY27 | G4: FY28 | H4: FY29 | I4: FY30 | J4: FY31
C5: 実績 | D5: 実績 | E5: 実績 | F5: 計画 | G5: 計画 | H5: 計画 | I5: 計画 | J5: 計画
B7: ストラクチャー
B8: エンタープライズ・バリュー（EV） | D8: 12000000
B9: エクイティ出資 | D9: 5500000
B10: シニアローン総額 | D10: 6500000
B11: うち参加金融機関A行 想定取組額 | D11: 2500000
B12: ローン期間（年） | D12: 7
B13: 適用金利（TIBOR+200bp想定） | D13: 0.022
B14: 約定弁済（年・最終回残額一括） | D14: 650000
B15: クローズ想定 | D15: 2026年9月末
B17: オペレーティング前提
B18: 実効税率 | D18: 0.31
B19: 売上債権回転日数 | D19: 45
B20: 買収時現金調整（取引費用等） | D20: -750000
B21: のれん想定額（暫定PPA前） | D21: 5500000
B23: スポンサー提示EBITDA（速報・ティーザー記載） | D23: 1585000
B24: （参考）旧前提 v2.1：シニア7,000,000／金利2.4% ※現行版では使用しない

Sheet PL
A1: 損益計算書（Projected P&L）
A2: （単位：千円） | H2: ケース: Sponsor Case
C4: FY24 | D4: FY25 | E4: FY26 | F4: FY27 | G4: FY28 | H4: FY29 | I4: FY30 | J4: FY31
C5: 実績 | D5: 実績 | E5: 実績 | F5: 計画 | G5: 計画 | H5: 計画 | I5: 計画 | J5: 計画
B7: 派遣事業売上 | C7: 12314768 | D7: 13205127 | E7: 13988621 | F7: =ROUND(KPI_Drivers!F9*KPI_Drivers!F10*KPI_Drivers!F11*12/1000,0) -> 15090595 | G7: =ROUND(KPI_Drivers!G9*KPI_Drivers!G10*KPI_Drivers!G11*12/1000,0) -> 16154323 | H7: =ROUND(KPI_Drivers!H9*KPI_Drivers!H10*KPI_Drivers!H11*12/1000,0) -> 17335093 | I7: =ROUND(KPI_Drivers!I9*KPI_Drivers!I10*KPI_Drivers!I11*12/1000,0) -> 18456744 | J7: =ROUND(KPI_Drivers!J9*KPI_Drivers!J10*KPI_Drivers!J11*12/1000,0) -> 19523104
B8: その他営業収入（紹介手数料等） | C8: 145232 | D8: 158000 | E8: 171379 | F8: 176092 | G8: 182000 | H8: 188000 | I8: 194000 | J8: 200000
B9: 売上高（Net Sales） | C9: =SUM(C7:C8) -> 12460000 | D9: =SUM(D7:D8) -> 13363127 | E9: =SUM(E7:E8) -> 14160000 | F9: =SUM(F7:F8) -> 15266687 | G9: =SUM(G7:G8) -> 16336323 | H9: =SUM(H7:H8) -> 17523093 | I9: =SUM(I7:I8) -> 18650744 | J9: =SUM(J7:J8) -> 19723104
B11: スタッフ労務費（法定福利費込） | C11: 9729886 | D11: 10413461 | E11: 11011043 | F11: =ROUND(KPI_Drivers!F9*KPI_Drivers!F10*KPI_Drivers!F12*(1+KPI_Drivers!F13)*12/1000,0) -> 11777011 | G11: =ROUND(KPI_Drivers!G9*KPI_Drivers!G10*KPI_Drivers!G12*(1+KPI_Drivers!G13)*12/1000,0) -> 12519452 | H11: =ROUND(KPI_Drivers!H9*KPI_Drivers!H10*KPI_Drivers!H12*(1+KPI_Drivers!H13)*12/1000,0) -> 13340688 | I11: =ROUND(KPI_Drivers!I9*KPI_Drivers!I10*KPI_Drivers!I12*(1+KPI_Drivers!I13)*12/1000,0) -> 14107670 | J11: =ROUND(KPI_Drivers!J9*KPI_Drivers!J10*KPI_Drivers!J12*(1+KPI_Drivers!J13)*12/1000,0) -> 14811844
B12: その他売上原価 | C12: 282000 | D12: 290000 | E12: 300000 | F12: 310000 | G12: 322000 | H12: 334000 | I12: 346000 | J12: 358000
B13: 売上原価 合計 | C13: =C11+C12 -> 10011886 | D13: =D11+D12 -> 10703461 | E13: =E11+E12 -> 11311043 | F13: =F11+F12 -> 12087011 | G13: =G11+G12 -> 12841452 | H13: =H11+H12 -> 13674688 | I13: =I11+I12 -> 14453670 | J13: =J11+J12 -> 15169844
B14: 売上総利益 | C14: =C9-C13 -> 2448114 | D14: =D9-D13 -> 2659666 | E14: =E9-E13 -> 2848957 | F14: =F9-F13 -> 3179676 | G14: =G9-G13 -> 3494871 | H14: =H9-H13 -> 3848405 | I14: =I9-I13 -> 4197074 | J14: =J9-J13 -> 4553260
B15: 売上総利益率 | C15: =C14/C9 -> 0.19647785 | D15: =D14/D9 -> 0.19903021 | E15: =E14/E9 -> 0.20119753 | F15: =F14/F9 -> 0.20827544 | G15: =G14/G9 -> 0.21393254 | H15: =H14/H9 -> 0.21961905 | I15: =I14/I9 -> 0.22503521 | J15: =J14/J9 -> 0.2308592
B17: 採用費 | C17: 236250 | D17: 266560 | E17: 295000 | F17: =KPI_Drivers!F14*KPI_Drivers!F15 -> 317520 | G17: =KPI_Drivers!G14*KPI_Drivers!G15 -> 330200 | H17: =KPI_Drivers!H14*KPI_Drivers!H15 -> 343040 | I17: =KPI_Drivers!I14*KPI_Drivers!I15 -> 354750 | J17: =KPI_Drivers!J14*KPI_Drivers!J15 -> 366600
B18: 本社人件費 | C18: 585000 | D18: 600000 | E18: 620000 | F18: 645000 | G18: 658000 | H18: 672000 | I18: 686000 | J18: 700000
B19: その他販管費 | C19: 398000 | D19: 405000 | E19: 419000 | F19: 432000 | G19: 436000 | H19: 440000 | I19: 444000 | J19: 448000
B20: 販売費及び一般管理費 合計 | C20: =SUM(C17:C19) -> 1219250 | D20: =SUM(D17:D19) -> 1271560 | E20: =SUM(E17:E19) -> 1334000 | F20: =SUM(F17:F19) -> 1394520 | G20: =SUM(G17:G19) -> 1424200 | H20: =SUM(H17:H19) -> 1455040 | I20: =SUM(I17:I19) -> 1484750 | J20: =SUM(J17:J19) -> 1514600
B21: 営業利益（Operating Profit） | C21: =C14-C20 -> 1228864 | D21: =D14-D20 -> 1388106 | E21: =E14-E20 -> 1514957 | F21: =F14-F20 -> 1785156 | G21: =G14-G20 -> 2070671 | H21: =H14-H20 -> 2393365 | I21: =I14-I20 -> 2712324 | J21: =J14-J20 -> 3038660
B22: 営業利益率 | C22: =C21/C9 -> 0.098624719 | D22: =D21/D9 -> 0.10387584 | E22: =E21/E9 -> 0.10698849 | F22: =F21/F9 -> 0.11693146 | G22: =G21/G9 -> 0.12675257 | H22: =H21/H9 -> 0.13658348 | I22: =I21/I9 -> 0.14542712 | J22: =J21/J9 -> 0.15406601
B24: 減価償却費 | C24: 92000 | D24: 98000 | E24: 105043 | F24: 113700 | G24: 117700 | H24: 121700 | I24: 125700 | J24: 129700
B25: Adj. EBITDA | C25: =C21+C24 -> 1320864 | D25: =D21+D24 -> 1486106 | E25: =E21+E24 -> 1620000 | F25: =F21+F24 -> 1898856 | G25: =G21+G24 -> 2188371 | H25: =H21+H24 -> 2515065 | I25: =I21+I24 -> 2838024 | J25: =J21+J24 -> 3168360
B26: EBITDAマージン | C26: =C25/C9 -> 0.10600835 | D26: =D25/D9 -> 0.11120945 | E26: =E25/E9 -> 0.11440678 | F26: =F25/F9 -> 0.12437905 | G26: =G25/G9 -> 0.13395738 | H26: =H25/H9 -> 0.1435286 | I26: =I25/I9 -> 0.1521668 | J26: =J25/J9 -> 0.16064206
B28: 支払利息 | C28: 14000 | D28: 13000 | E28: 12000 | F28: =Debt_Schedule!F12 -> 135850 | G28: =Debt_Schedule!G12 -> 121550 | H28: =Debt_Schedule!H12 -> 107250 | I28: =Debt_Schedule!I12 -> 92950 | J28: =Debt_Schedule!J12 -> 78650
B29: 営業外損益（純額） | C29: 4800 | D29: 5200 | E29: 5500 | F29: 6000 | G29: 6000 | H29: 6000 | I29: 6000 | J29: 6000
B30: 経常利益 | C30: =C21-C28+C29 -> 1219664 | D30: =D21-D28+D29 -> 1380306 | E30: =E21-E28+E29 -> 1508457 | F30: =F21-F28+F29 -> 1655306 | G30: =G21-G28+G29 -> 1955121 | H30: =H21-H28+H29 -> 2292115 | I30: =I21-I28+I29 -> 2625374 | J30: =J21-J28+J29 -> 2966010
B31: 法人税等（実効税率31%） | C31: =ROUND(C30*0.31,0) -> 378096 | D31: =ROUND(D30*0.31,0) -> 427895 | E31: =ROUND(E30*0.31,0) -> 467622 | F31: =ROUND(F30*0.31,0) -> 513145 | G31: =ROUND(G30*0.31,0) -> 606088 | H31: =ROUND(H30*0.31,0) -> 710556 | I31: =ROUND(I30*0.31,0) -> 813866 | J31: =ROUND(J30*0.31,0) -> 919463
B32: 当期純利益 | C32: =C30-C31 -> 841568 | D32: =D30-D31 -> 952411 | E32: =E30-E31 -> 1040835 | F32: =F30-F31 -> 1142161 | G32: =G30-G31 -> 1349033 | H32: =H30-H31 -> 1581559 | I32: =I30-I31 -> 1811508 | J32: =J30-J31 -> 2046547

Sheet BS
A1: 貸借対照表（Projected B/S）
A2: （単位：千円） | H2: ケース: Sponsor Case
C4: FY24 | D4: FY25 | E4: FY26 | F4: FY27 | G4: FY28 | H4: FY29 | I4: FY30 | J4: FY31
C5: 実績 | D5: 実績 | E5: 実績 | F5: 計画 | G5: 計画 | H5: 計画 | I5: 計画 | J5: 計画
B7: 現金及び預金 | C7: 1420000 | D7: 1640000 | E7: 1850000 | F7: 1523861 | G7: 2113594 | H7: 2930853 | I7: 3989061 | J7: 5292308
B8: 売上債権 | C8: 1540000 | D8: 1650000 | E8: 1750000 | F8: 1882000 | G8: 2014000 | H8: 2160000 | I8: 2299000 | J8: 2432000
B9: その他流動資産 | C9: 180000 | D9: 190000 | E9: 200000 | F9: 210000 | G9: 215000 | H9: 220000 | I9: 225000 | J9: 230000
B10: 流動資産 合計 | C10: =SUM(C7:C9) -> 3140000 | D10: =SUM(D7:D9) -> 3480000 | E10: =SUM(E7:E9) -> 3800000 | F10: =SUM(F7:F9) -> 3615861 | G10: =SUM(G7:G9) -> 4342594 | H10: =SUM(H7:H9) -> 5310853 | I10: =SUM(I7:I9) -> 6513061 | J10: =SUM(J7:J9) -> 7954308
B12: 有形固定資産 | C12: 820000 | D12: 840000 | E12: 860000 | F12: 886300 | G12: 908600 | H12: 926900 | I12: 941200 | J12: 951500
B13: のれん（Goodwill） | C13: 0 | D13: 0 | E13: 0 | F13: 5500000 | G13: 5500000 | H13: 5500000 | I13: 5500000 | J13: 5500000
B14: 無形固定資産・その他 | C14: 260000 | D14: 270000 | E14: 280000 | F14: 290000 | G14: 290000 | H14: 290000 | I14: 290000 | J14: 290000
B15: 固定資産 合計 | C15: =SUM(C12:C14) -> 1080000 | D15: =SUM(D12:D14) -> 1110000 | E15: =SUM(E12:E14) -> 1140000 | F15: =SUM(F12:F14) -> 6676300 | G15: =SUM(G12:G14) -> 6698600 | H15: =SUM(H12:H14) -> 6716900 | I15: =SUM(I12:I14) -> 6731200 | J15: =SUM(J12:J14) -> 6741500
B16: 資産合計 | C16: =C10+C15 -> 4220000 | D16: =D10+D15 -> 4590000 | E16: =E10+E15 -> 4940000 | F16: =F10+F15 -> 10292161 | G16: =G10+G15 -> 11041194 | H16: =H10+H15 -> 12027753 | I16: =I10+I15 -> 13244261 | J16: =J10+J15 -> 14695808
B18: 仕入債務・未払費用 | C18: 1080000 | D18: 1130000 | E18: 1180000 | F18: 1270000 | G18: 1320000 | H18: 1375000 | I18: 1430000 | J18: 1485000
B19: その他負債 | C19: 790000 | D19: 550000 | E19: 310000 | F19: 320000 | G19: 320000 | H19: 320000 | I19: 320000 | J19: 320000
B20: 有利子負債 | C20: 400000 | D20: 350000 | E20: 300000 | F20: =Debt_Schedule!F9 -> 5850000 | G20: =Debt_Schedule!G9 -> 5200000 | H20: =Debt_Schedule!H9 -> 4550000 | I20: =Debt_Schedule!I9 -> 3900000 | J20: =Debt_Schedule!J9 -> 3250000
B21: 負債合計 | C21: =SUM(C18:C20) -> 2270000 | D21: =SUM(D18:D20) -> 2030000 | E21: =SUM(E18:E20) -> 1790000 | F21: =SUM(F18:F20) -> 7440000 | G21: =SUM(G18:G20) -> 6840000 | H21: =SUM(H18:H20) -> 6245000 | I21: =SUM(I18:I20) -> 5650000 | J21: =SUM(J18:J20) -> 5055000
B23: 純資産（Net Assets） | C23: 1950000 | D23: 2560000 | E23: 3150000 | F23: 2852161 | G23: 4201194 | H23: 5782753 | I23: 7594261 | J23: 9640808
B24: 負債純資産合計 | C24: =C21+C23 -> 4220000 | D24: =D21+D23 -> 4590000 | E24: =E21+E23 -> 4940000 | F24: =F21+F23 -> 10292161 | G24: =G21+G23 -> 11041194 | H24: =H21+H23 -> 12027753 | I24: =I21+I23 -> 13244261 | J24: =J21+J23 -> 14695808
B26: ※ FY27以降は買収後連結（のれん計上・買収時調整を純資産に含む）。のれんは暫定PPA前の想定額。

Sheet CF
A1: キャッシュフロー計算書（Projected C/F）
A2: （単位：千円） | H2: ケース: Sponsor Case
C4: FY24 | D4: FY25 | E4: FY26 | F4: FY27 | G4: FY28 | H4: FY29 | I4: FY30 | J4: FY31
C5: 実績 | D5: 実績 | E5: 実績 | F5: 計画 | G5: 計画 | H5: 計画 | I5: 計画 | J5: 計画
B7: 税引後当期純利益 | C7: =PL!C32 -> 841568 | D7: =PL!D32 -> 952411 | E7: =PL!E32 -> 1040835 | F7: =PL!F32 -> 1142161 | G7: =PL!G32 -> 1349033 | H7: =PL!H32 -> 1581559 | I7: =PL!I32 -> 1811508 | J7: =PL!J32 -> 2046547
B8: 減価償却費 | C8: =PL!C24 -> 92000 | D8: =PL!D24 -> 98000 | E8: =PL!E24 -> 105043 | F8: =PL!F24 -> 113700 | G8: =PL!G24 -> 117700 | H8: =PL!H24 -> 121700 | I8: =PL!I24 -> 125700 | J8: =PL!J24 -> 129700
B9: 運転資本増減・その他（△増加） | C9: 216432 | D9: 239589 | E9: 274122 | F9: -52000 | G9: -87000 | H9: -96000 | I9: -89000 | J9: -83000
B10: 営業キャッシュフロー | C10: =SUM(C7:C9) -> 1150000 | D10: =SUM(D7:D9) -> 1290000 | E10: =SUM(E7:E9) -> 1420000 | F10: =SUM(F7:F9) -> 1203861 | G10: =SUM(G7:G9) -> 1379733 | H10: =SUM(H7:H9) -> 1607259 | I10: =SUM(I7:I9) -> 1848208 | J10: =SUM(J7:J9) -> 2093247
B12: 設備投資等（投資CF） | C12: -100000 | D12: -110000 | E12: -115000 | F12: -140000 | G12: -140000 | H12: -140000 | I12: -140000 | J12: -140000
B13: フリー・キャッシュフロー（FCF） | C13: =C10+C12 -> 1050000 | D13: =D10+D12 -> 1180000 | E13: =E10+E12 -> 1305000 | F13: =F10+F12 -> 1063861 | G13: =G10+G12 -> 1239733 | H13: =H10+H12 -> 1467259 | I13: =I10+I12 -> 1708208 | J13: =J10+J12 -> 1953247
B15: 借入金返済 | C15: -50000 | D15: -50000 | E15: -50000 | F15: =-Debt_Schedule!F8 -> -650000 | G15: =-Debt_Schedule!G8 -> -650000 | H15: =-Debt_Schedule!H8 -> -650000 | I15: =-Debt_Schedule!I8 -> -650000 | J15: =-Debt_Schedule!J8 -> -650000
B16: 配当・その他財務 | C16: -880000 | D16: -910000 | E16: -1045000 | F16: 10000 | G16: 0 | H16: 0 | I16: 0 | J16: 0
B17: 財務キャッシュフロー | C17: =C15+C16 -> -930000 | D17: =D15+D16 -> -960000 | E17: =E15+E16 -> -1095000 | F17: =F15+F16 -> -640000 | G17: =G15+G16 -> -650000 | H17: =H15+H16 -> -650000 | I17: =I15+I16 -> -650000 | J17: =J15+J16 -> -650000
B19: 現金増減 | C19: =C13+C17 -> 120000 | D19: =D13+D17 -> 220000 | E19: =E13+E17 -> 210000 | F19: =F13+F17 -> 423861 | G19: =G13+G17 -> 589733 | H19: =H13+H17 -> 817259 | I19: =I13+I17 -> 1058208 | J19: =J13+J17 -> 1303247
B20: 期首現金 | C20: 1300000 | D20: =C21 -> 1420000 | E20: =D21 -> 1640000 | F20: 1100000 | G20: =F21 -> 1523861 | H20: =G21 -> 2113594 | I20: =H21 -> 2930853 | J20: =I21 -> 3989061
B21: 期末現金 | C21: =C19+C20 -> 1420000 | D21: =D19+D20 -> 1640000 | E21: =E19+E20 -> 1850000 | F21: =F19+F20 -> 1523861 | G21: =G19+G20 -> 2113594 | H21: =H19+H20 -> 2930853 | I21: =I19+I20 -> 3989061 | J21: =J19+J20 -> 5292308
B24: ※ FY27期首現金は買収時調整後（取引費用等750,000千円控除後）。

Sheet KPI_Drivers
A1: KPIドライバー（Operating Assumptions）
A2: （単位：名・時間・円・％） | H2: ケース: Sponsor Case
C4: FY24 | D4: FY25 | E4: FY26 | F4: FY27 | G4: FY28 | H4: FY29 | I4: FY30 | J4: FY31
C5: 実績 | D5: 実績 | E5: 実績 | F5: 計画 | G5: 計画 | H5: 計画 | I5: 計画 | J5: 計画
B7: 在籍登録スタッフ数（名） | C7: 3560 | D7: 3690 | E7: 3800 | F7: 4000 | G7: 4180 | H7: 4350 | I7: 4520 | J7: 4690
B8: 稼働率（Utilization） | C8: 0.865 | D8: 0.872 | E8: 0.88 | F8: 0.885 | G8: 0.89 | H8: 0.895 | I8: 0.9 | J8: 0.9
B9: 稼働人数（名） | C9: =ROUND(C7*C8,0) -> 3079 | D9: =ROUND(D7*D8,0) -> 3218 | E9: =ROUND(E7*E8,0) -> 3344 | F9: =ROUND(F7*F8,0) -> 3540 | G9: =ROUND(G7*G8,0) -> 3720 | H9: =ROUND(H7*H8,0) -> 3893 | I9: =ROUND(I7*I8,0) -> 4068 | J9: =ROUND(J7*J8,0) -> 4221
B10: 月間平均稼働時間（h/名） | C10: 165 | D10: 166 | E10: 166 | F10: 166 | G10: 166 | H10: 167 | I10: 167 | J10: 167
B11: 派遣単価（円/h） | C11: 2020 | D11: 2060 | E11: 2100 | F11: 2140 | G11: 2180 | H11: 2222 | I11: 2264 | J11: 2308
B12: スタッフ平均時給（円/h） | C12: 1400 | D12: 1425 | E12: 1450 | F12: 1465 | G12: 1482 | H12: 1500 | I12: 1518 | J12: 1536
B13: 法定福利費率 | C13: 0.14 | D13: 0.14 | E13: 0.14 | F13: 0.14 | G13: 0.14 | H13: 0.14 | I13: 0.14 | J13: 0.14
B14: 新規採用人数（名） | C14: 1050 | D14: 1120 | E14: 1180 | F14: 1260 | G14: 1300 | H14: 1340 | I14: 1375 | J14: 1410
B15: 採用単価（CPA・千円/名） | C15: 225 | D15: 238 | E15: 250 | F15: 252 | G15: 254 | H15: 256 | I15: 258 | J15: 260
B16: 離職率（年間） | C16: 0.24 | D16: 0.23 | E16: 0.22 | F16: 0.22 | G16: 0.21 | H16: 0.2 | I16: 0.195 | J16: 0.19
B18: ※ 稼働人数 = 在籍登録スタッフ数 × 稼働率（四捨五入）

Sheet Debt_Schedule
A1: デットスケジュール（シニアローン）
A2: （単位：千円） | H2: ケース: Sponsor Case
C4: FY24 | D4: FY25 | E4: FY26 | F4: FY27 | G4: FY28 | H4: FY29 | I4: FY30 | J4: FY31
C5: 実績 | D5: 実績 | E5: 実績 | F5: 計画 | G5: 計画 | H5: 計画 | I5: 計画 | J5: 計画
B7: 期首残高 | F7: 6500000 | G7: =F9 -> 5850000 | H7: =G9 -> 5200000 | I7: =H9 -> 4550000 | J7: =I9 -> 3900000
B8: 約定弁済 | F8: 650000 | G8: 650000 | H8: 650000 | I8: 650000 | J8: 650000
B9: 期末残高 | F9: =F7-F8 -> 5850000 | G9: =G7-G8 -> 5200000 | H9: =H7-H8 -> 4550000 | I9: =I7-I8 -> 3900000 | J9: =J7-J8 -> 3250000
B10: 平均残高 | F10: =(F7+F9)/2 -> 6175000 | G10: =(G7+G9)/2 -> 5525000 | H10: =(H7+H9)/2 -> 4875000 | I10: =(I7+I9)/2 -> 4225000 | J10: =(J7+J9)/2 -> 3575000
B11: 適用金利（TIBOR+200bp想定） | F11: 0.022 | G11: 0.022 | H11: 0.022 | I11: 0.022 | J11: 0.022
B12: 支払利息 | F12: =ROUND(F10*F11,0) -> 135850 | G12: =ROUND(G10*G11,0) -> 121550 | H12: =ROUND(H10*H11,0) -> 107250 | I12: =ROUND(I10*I11,0) -> 92950 | J12: =ROUND(J10*J11,0) -> 78650
B14: ※ 約定弁済は年650,000千円、最終回（FY33）残額一括。実績年欄は対象外。

Sheet PL_old
A1: 損益計算書【旧版 v2.1】※使用しないこと（FY26速報反映前）
A2: （単位：千円） | H2: ケース: Sponsor Case
C4: FY24 | D4: FY25 | E4: FY26 | F4: FY27 | G4: FY28 | H4: FY29 | I4: FY30 | J4: FY31
C5: 実績 | D5: 実績 | E5: 実績 | F5: 計画 | G5: 計画 | H5: 計画 | I5: 計画 | J5: 計画
B7: 派遣事業売上 | C7: 11883751 | D7: 12742947 | E7: 13499019 | F7: 14562424 | G7: 15588921 | H7: 16728364 | I7: 17810757 | J7: 18839795
B8: その他営業収入（紹介手数料等） | C8: 140148 | D8: 152470 | E8: 165380 | F8: 169928 | G8: 175630 | H8: 181420 | I8: 187210 | J8: 193000
B9: 売上高（Net Sales） | C9: 12023900 | D9: 12895417 | E9: 13664400 | F9: 14732352 | G9: 15764551 | H9: 16909784 | I9: 17997967 | J9: 19032795
B11: スタッフ労務費（法定福利費込） | C11: 9389339 | D11: 10048989 | E11: 10625656 | F11: 11364815 | G11: 12081271 | H11: 12873763 | I11: 13613901 | J11: 14293429
B13: 売上原価 合計 | C13: 9661469 | D13: 10328839 | E13: 10915156 | F13: 11663965 | G13: 12392001 | H13: 13196073 | I13: 13947791 | J13: 14638899
B14: 売上総利益 | C14: 2362430 | D14: 2566577 | E14: 2749243 | F14: 3068387 | G14: 3372550 | H14: 3713710 | I14: 4050176 | J14: 4393895
B20: 販売費及び一般管理費 合計 | C20: 1176576 | D20: 1227055 | E20: 1287310 | F20: 1345711 | G20: 1374353 | H20: 1404113 | I20: 1432783 | J20: 1461589
B21: 営業利益（Operating Profit） | C21: 1185853 | D21: 1339522 | E21: 1461933 | F21: 1722675 | G21: 1998197 | H21: 2309597 | I21: 2617392 | J21: 2932306
B24: 減価償却費 | C24: 88780 | D24: 94570 | E24: 101366 | F24: 109720 | G24: 113580 | H24: 117440 | I24: 121300 | J24: 125160
B25: Adj. EBITDA | C25: 1274633 | D25: 1434092 | E25: 1563300 | F25: 1832396 | G25: 2111778 | H25: 2427037 | I25: 2738693 | J25: 3057467
B32: 当期純利益 | C32: 812113 | D32: 919076 | E32: 1004405 | F32: 1102185 | G32: 1301816 | H32: 1526204 | I32: 1748105 | J32: 1974917

Sheet Scratch
A1: （作業用シート・成果物ではありません）
B3: チェック: 3,344×166×2,100×12 = | D3: 13988620800
B4: → PL派遣売上と一致確認済（6/25 IY）
B6: TODO: 労務費の福利率 13.8%→14.0%に更新（6/28 反映済）
B8: 単価改定メモ: トヨタ系 4月改定 +1.2%規定 / デンソー系 10月
B10: 4233600 | C10: ←年間換算係数（166h×2,125×12）ミス。使わない
B12: 旧のれん試算 5,656,000 → PPA仮 5,500,000

Sheet Sheet1
